{
  "gru": {
    "name": "gru",
    "val_mae": null,
    "test_mae": 0.3659860964738186,
    "audit_mae": 0.33489253739209485,
    "test_skill": 0.7578237394709593,
    "audit_skill": 0.7362896731202526,
    "per_horizon_test": [
      {
        "horizon_h": 1,
        "mae": 0.11305793305517925,
        "n": 142
      },
      {
        "horizon_h": 2,
        "mae": 0.13169035302831775,
        "n": 188
      },
      {
        "horizon_h": 3,
        "mae": 0.14511373829959057,
        "n": 203
      },
      {
        "horizon_h": 4,
        "mae": 0.17593131739918777,
        "n": 205
      },
      {
        "horizon_h": 5,
        "mae": 0.1924621999560304,
        "n": 201
      },
      {
        "horizon_h": 6,
        "mae": 0.22067947633804816,
        "n": 155
      },
      {
        "horizon_h": 7,
        "mae": 0.23494187475929793,
        "n": 142
      },
      {
        "horizon_h": 8,
        "mae": 0.20679128017831352,
        "n": 188
      },
      {
        "horizon_h": 9,
        "mae": 0.21823557485448256,
        "n": 202
      },
      {
        "horizon_h": 10,
        "mae": 0.21795429622425755,
        "n": 204
      },
      {
        "horizon_h": 11,
        "mae": 0.22980385396017955,
        "n": 201
      },
      {
        "horizon_h": 12,
        "mae": 0.19458139221389575,
        "n": 154
      },
      {
        "horizon_h": 13,
        "mae": 0.2026717395647198,
        "n": 141
      },
      {
        "horizon_h": 14,
        "mae": 0.19771000561229685,
        "n": 187
      },
      {
        "horizon_h": 15,
        "mae": 0.2066836447265018,
        "n": 201
      },
      {
        "horizon_h": 16,
        "mae": 0.2101429220490855,
        "n": 203
      },
      {
        "horizon_h": 17,
        "mae": 0.224758131980896,
        "n": 200
      },
      {
        "horizon_h": 18,
        "mae": 0.2115705901501225,
        "n": 153
      },
      {
        "horizon_h": 19,
        "mae": 0.22315671934303669,
        "n": 141
      },
      {
        "horizon_h": 20,
        "mae": 0.24264488730201103,
        "n": 187
      },
      {
        "horizon_h": 21,
        "mae": 0.24447097968106254,
        "n": 201
      },
      {
        "horizon_h": 22,
        "mae": 0.24367937266533013,
        "n": 203
      },
      {
        "horizon_h": 23,
        "mae": 0.2682317572446605,
        "n": 201
      },
      {
        "horizon_h": 24,
        "mae": 0.26166988967301,
        "n": 154
      },
      {
        "horizon_h": 25,
        "mae": 0.2714006015232631,
        "n": 140
      },
      {
        "horizon_h": 26,
        "mae": 0.26370031681466605,
        "n": 188
      },
      {
        "horizon_h": 27,
        "mae": 0.26795690460960464,
        "n": 202
      },
      {
        "horizon_h": 28,
        "mae": 0.2654433424249658,
        "n": 203
      },
      {
        "horizon_h": 29,
        "mae": 0.28896078449664725,
        "n": 202
      },
      {
        "horizon_h": 30,
        "mae": 0.28901900621800636,
        "n": 153
      },
      {
        "horizon_h": 31,
        "mae": 0.30468433243887766,
        "n": 140
      },
      {
        "horizon_h": 32,
        "mae": 0.2852948442418524,
        "n": 188
      },
      {
        "horizon_h": 33,
        "mae": 0.2859851487792364,
        "n": 202
      },
      {
        "horizon_h": 34,
        "mae": 0.2845935793206243,
        "n": 202
      },
      {
        "horizon_h": 35,
        "mae": 0.29711924637898357,
        "n": 202
      },
      {
        "horizon_h": 36,
        "mae": 0.2778067669837303,
        "n": 153
      },
      {
        "horizon_h": 37,
        "mae": 0.29263245037623814,
        "n": 140
      },
      {
        "horizon_h": 38,
        "mae": 0.28830632608403595,
        "n": 189
      },
      {
        "horizon_h": 39,
        "mae": 0.28367394456768985,
        "n": 202
      },
      {
        "horizon_h": 40,
        "mae": 0.2767298339617134,
        "n": 202
      },
      {
        "horizon_h": 41,
        "mae": 0.3041871797920453,
        "n": 202
      },
      {
        "horizon_h": 42,
        "mae": 0.2908464880550609,
        "n": 153
      },
      {
        "horizon_h": 43,
        "mae": 0.2989098344530378,
        "n": 140
      },
      {
        "horizon_h": 44,
        "mae": 0.3074997962789332,
        "n": 188
      },
      {
        "horizon_h": 45,
        "mae": 0.307563066010428,
        "n": 202
      },
      {
        "horizon_h": 46,
        "mae": 0.3039180613980435,
        "n": 202
      },
      {
        "horizon_h": 47,
        "mae": 0.3283025458307549,
        "n": 202
      },
      {
        "horizon_h": 48,
        "mae": 0.32305545308231526,
        "n": 153
      },
      {
        "horizon_h": 49,
        "mae": 0.33716344765737544,
        "n": 141
      },
      {
        "horizon_h": 50,
        "mae": 0.3259641555541339,
        "n": 187
      },
      {
        "horizon_h": 51,
        "mae": 0.3198893494866974,
        "n": 201
      },
      {
        "horizon_h": 52,
        "mae": 0.3177872719456307,
        "n": 201
      },
      {
        "horizon_h": 53,
        "mae": 0.33217041053582186,
        "n": 201
      },
      {
        "horizon_h": 54,
        "mae": 0.3234055234896426,
        "n": 151
      },
      {
        "horizon_h": 55,
        "mae": 0.33422887139286556,
        "n": 141
      },
      {
        "horizon_h": 56,
        "mae": 0.3250404337510705,
        "n": 187
      },
      {
        "horizon_h": 57,
        "mae": 0.32096246403066364,
        "n": 199
      },
      {
        "horizon_h": 58,
        "mae": 0.31386152428774095,
        "n": 201
      },
      {
        "horizon_h": 59,
        "mae": 0.33456299114227295,
        "n": 200
      },
      {
        "horizon_h": 60,
        "mae": 0.3252142499287924,
        "n": 150
      },
      {
        "horizon_h": 61,
        "mae": 0.3300998251778739,
        "n": 140
      },
      {
        "horizon_h": 62,
        "mae": 0.3131117203656365,
        "n": 187
      },
      {
        "horizon_h": 63,
        "mae": 0.3142218310423572,
        "n": 198
      },
      {
        "horizon_h": 64,
        "mae": 0.30910679531097407,
        "n": 200
      },
      {
        "horizon_h": 65,
        "mae": 0.33394271908093925,
        "n": 199
      },
      {
        "horizon_h": 66,
        "mae": 0.32328416570027674,
        "n": 150
      },
      {
        "horizon_h": 67,
        "mae": 0.3373617185963144,
        "n": 139
      },
      {
        "horizon_h": 68,
        "mae": 0.3352845860037575,
        "n": 187
      },
      {
        "horizon_h": 69,
        "mae": 0.3428782822498724,
        "n": 199
      },
      {
        "horizon_h": 70,
        "mae": 0.33703004163296063,
        "n": 201
      },
      {
        "horizon_h": 71,
        "mae": 0.35553575801849363,
        "n": 200
      },
      {
        "horizon_h": 72,
        "mae": 0.34823840332031253,
        "n": 150
      },
      {
        "horizon_h": 73,
        "mae": 0.3542020933968681,
        "n": 140
      },
      {
        "horizon_h": 74,
        "mae": 0.3434144392370541,
        "n": 187
      },
      {
        "horizon_h": 75,
        "mae": 0.3451246328689345,
        "n": 199
      },
      {
        "horizon_h": 76,
        "mae": 0.3341229481483573,
        "n": 201
      },
      {
        "horizon_h": 77,
        "mae": 0.3532266988754272,
        "n": 200
      },
      {
        "horizon_h": 78,
        "mae": 0.3449101569668559,
        "n": 149
      },
      {
        "horizon_h": 79,
        "mae": 0.3502184408174145,
        "n": 139
      },
      {
        "horizon_h": 80,
        "mae": 0.3444493064268388,
        "n": 187
      },
      {
        "horizon_h": 81,
        "mae": 0.3465891564910735,
        "n": 199
      },
      {
        "horizon_h": 82,
        "mae": 0.3494765133114915,
        "n": 199
      },
      {
        "horizon_h": 83,
        "mae": 0.37077626750696846,
        "n": 199
      },
      {
        "horizon_h": 84,
        "mae": 0.34822562965186865,
        "n": 148
      },
      {
        "horizon_h": 85,
        "mae": 0.35554386636485225,
        "n": 138
      },
      {
        "horizon_h": 86,
        "mae": 0.3499691233915442,
        "n": 187
      },
      {
        "horizon_h": 87,
        "mae": 0.3557830579353101,
        "n": 198
      },
      {
        "horizon_h": 88,
        "mae": 0.35119667053222653,
        "n": 198
      },
      {
        "horizon_h": 89,
        "mae": 0.37185484471947255,
        "n": 198
      },
      {
        "horizon_h": 90,
        "mae": 0.35535927978721826,
        "n": 148
      },
      {
        "horizon_h": 91,
        "mae": 0.3616672975303484,
        "n": 137
      },
      {
        "horizon_h": 92,
        "mae": 0.3617924919740401,
        "n": 187
      },
      {
        "horizon_h": 93,
        "mae": 0.36292233996921114,
        "n": 198
      },
      {
        "horizon_h": 94,
        "mae": 0.35649242015800087,
        "n": 198
      },
      {
        "horizon_h": 95,
        "mae": 0.376057374356973,
        "n": 198
      },
      {
        "horizon_h": 96,
        "mae": 0.35928599428968366,
        "n": 147
      },
      {
        "horizon_h": 97,
        "mae": 0.3765059189830752,
        "n": 139
      },
      {
        "horizon_h": 98,
        "mae": 0.3743488585695307,
        "n": 188
      },
      {
        "horizon_h": 99,
        "mae": 0.3700428267819198,
        "n": 199
      },
      {
        "horizon_h": 100,
        "mae": 0.3724703553932995,
        "n": 199
      },
      {
        "horizon_h": 101,
        "mae": 0.39455259505228774,
        "n": 199
      },
      {
        "horizon_h": 102,
        "mae": 0.3660522006806873,
        "n": 147
      },
      {
        "horizon_h": 103,
        "mae": 0.38954234745191496,
        "n": 138
      },
      {
        "horizon_h": 104,
        "mae": 0.39093606232335326,
        "n": 189
      },
      {
        "horizon_h": 105,
        "mae": 0.3906320092666089,
        "n": 199
      },
      {
        "horizon_h": 106,
        "mae": 0.3895101051330566,
        "n": 200
      },
      {
        "horizon_h": 107,
        "mae": 0.41540099484237586,
        "n": 199
      },
      {
        "horizon_h": 108,
        "mae": 0.3778887288100054,
        "n": 147
      },
      {
        "horizon_h": 109,
        "mae": 0.3976268448098733,
        "n": 137
      },
      {
        "horizon_h": 110,
        "mae": 0.4033968607584635,
        "n": 189
      },
      {
        "horizon_h": 111,
        "mae": 0.39918772539301733,
        "n": 199
      },
      {
        "horizon_h": 112,
        "mae": 0.3997304944992065,
        "n": 200
      },
      {
        "horizon_h": 113,
        "mae": 0.4236210492388087,
        "n": 199
      },
      {
        "horizon_h": 114,
        "mae": 0.38911012829961006,
        "n": 148
      },
      {
        "horizon_h": 115,
        "mae": 0.40230376616768215,
        "n": 138
      },
      {
        "horizon_h": 116,
        "mae": 0.4232334328706933,
        "n": 189
      },
      {
        "horizon_h": 117,
        "mae": 0.41827112130783317,
        "n": 199
      },
      {
        "horizon_h": 118,
        "mae": 0.4199940700531005,
        "n": 200
      },
      {
        "horizon_h": 119,
        "mae": 0.43772532688313387,
        "n": 199
      },
      {
        "horizon_h": 120,
        "mae": 0.4133821007345809,
        "n": 147
      },
      {
        "horizon_h": 121,
        "mae": 0.4285482255674952,
        "n": 139
      },
      {
        "horizon_h": 122,
        "mae": 0.43440974012334294,
        "n": 188
      },
      {
        "horizon_h": 123,
        "mae": 0.4307299064867425,
        "n": 198
      },
      {
        "horizon_h": 124,
        "mae": 0.4397428042924583,
        "n": 199
      },
      {
        "horizon_h": 125,
        "mae": 0.4610420284849224,
        "n": 198
      },
      {
        "horizon_h": 126,
        "mae": 0.4177084771518049,
        "n": 145
      },
      {
        "horizon_h": 127,
        "mae": 0.4443448785422505,
        "n": 138
      },
      {
        "horizon_h": 128,
        "mae": 0.45327148944773576,
        "n": 188
      },
      {
        "horizon_h": 129,
        "mae": 0.45142284238398983,
        "n": 197
      },
      {
        "horizon_h": 130,
        "mae": 0.4571373111069804,
        "n": 198
      },
      {
        "horizon_h": 131,
        "mae": 0.47452322383822515,
        "n": 197
      },
      {
        "horizon_h": 132,
        "mae": 0.42586161957846747,
        "n": 144
      },
      {
        "horizon_h": 133,
        "mae": 0.4450840177327177,
        "n": 137
      },
      {
        "horizon_h": 134,
        "mae": 0.4715908886914585,
        "n": 187
      },
      {
        "horizon_h": 135,
        "mae": 0.46619332115057155,
        "n": 197
      },
      {
        "horizon_h": 136,
        "mae": 0.46985217971031107,
        "n": 198
      },
      {
        "horizon_h": 137,
        "mae": 0.49229150762412754,
        "n": 197
      },
      {
        "horizon_h": 138,
        "mae": 0.4413066324694403,
        "n": 145
      },
      {
        "horizon_h": 139,
        "mae": 0.4515818360922993,
        "n": 138
      },
      {
        "horizon_h": 140,
        "mae": 0.48764015867355026,
        "n": 188
      },
      {
        "horizon_h": 141,
        "mae": 0.4829469854181464,
        "n": 198
      },
      {
        "horizon_h": 142,
        "mae": 0.4788448717126894,
        "n": 199
      },
      {
        "horizon_h": 143,
        "mae": 0.5043491854812159,
        "n": 198
      },
      {
        "horizon_h": 144,
        "mae": 0.45849624765330343,
        "n": 145
      },
      {
        "horizon_h": 145,
        "mae": 0.4775264104207357,
        "n": 138
      },
      {
        "horizon_h": 146,
        "mae": 0.5027044661501621,
        "n": 188
      },
      {
        "horizon_h": 147,
        "mae": 0.5019820685338493,
        "n": 198
      },
      {
        "horizon_h": 148,
        "mae": 0.5050724863407,
        "n": 199
      },
      {
        "horizon_h": 149,
        "mae": 0.5290755262278547,
        "n": 198
      },
      {
        "horizon_h": 150,
        "mae": 0.4926580336358811,
        "n": 144
      },
      {
        "horizon_h": 151,
        "mae": 0.5171351161316363,
        "n": 137
      },
      {
        "horizon_h": 152,
        "mae": 0.5288447298902147,
        "n": 188
      },
      {
        "horizon_h": 153,
        "mae": 0.5258252903894725,
        "n": 197
      },
      {
        "horizon_h": 154,
        "mae": 0.5248675741330541,
        "n": 198
      },
      {
        "horizon_h": 155,
        "mae": 0.5463877518164929,
        "n": 197
      },
      {
        "horizon_h": 156,
        "mae": 0.5028922594510592,
        "n": 143
      },
      {
        "horizon_h": 157,
        "mae": 0.5156867770587696,
        "n": 136
      },
      {
        "horizon_h": 158,
        "mae": 0.5396767646708387,
        "n": 188
      },
      {
        "horizon_h": 159,
        "mae": 0.5356814335803597,
        "n": 196
      },
      {
        "horizon_h": 160,
        "mae": 0.5379578856647317,
        "n": 197
      },
      {
        "horizon_h": 161,
        "mae": 0.5573599406651087,
        "n": 196
      },
      {
        "horizon_h": 162,
        "mae": 0.51017480691274,
        "n": 144
      },
      {
        "horizon_h": 163,
        "mae": 0.5199565354515524,
        "n": 136
      },
      {
        "horizon_h": 164,
        "mae": 0.5489362947564377,
        "n": 190
      },
      {
        "horizon_h": 165,
        "mae": 0.5451617700799468,
        "n": 197
      },
      {
        "horizon_h": 166,
        "mae": 0.5515372998786695,
        "n": 198
      },
      {
        "horizon_h": 167,
        "mae": 0.5723550748098925,
        "n": 197
      },
      {
        "horizon_h": 168,
        "mae": 0.5318012106007542,
        "n": 145
      }
    ],
    "per_horizon_audit": [
      {
        "horizon_h": 1,
        "mae": 0.09989483356475826,
        "n": 128
      },
      {
        "horizon_h": 2,
        "mae": 0.11825319031375127,
        "n": 199
      },
      {
        "horizon_h": 3,
        "mae": 0.13427520541090468,
        "n": 199
      },
      {
        "horizon_h": 4,
        "mae": 0.16888289427637465,
        "n": 199
      },
      {
        "horizon_h": 5,
        "mae": 0.19267569561393888,
        "n": 196
      },
      {
        "horizon_h": 6,
        "mae": 0.1979595154050797,
        "n": 126
      },
      {
        "horizon_h": 7,
        "mae": 0.2171908581350732,
        "n": 127
      },
      {
        "horizon_h": 8,
        "mae": 0.18767537974347973,
        "n": 198
      },
      {
        "horizon_h": 9,
        "mae": 0.20182845568416102,
        "n": 198
      },
      {
        "horizon_h": 10,
        "mae": 0.216036171383328,
        "n": 198
      },
      {
        "horizon_h": 11,
        "mae": 0.23330081352820764,
        "n": 195
      },
      {
        "horizon_h": 12,
        "mae": 0.21242449624197826,
        "n": 126
      },
      {
        "horizon_h": 13,
        "mae": 0.22757628583532627,
        "n": 127
      },
      {
        "horizon_h": 14,
        "mae": 0.2188562383555402,
        "n": 198
      },
      {
        "horizon_h": 15,
        "mae": 0.23709513924338607,
        "n": 198
      },
      {
        "horizon_h": 16,
        "mae": 0.22955975099043419,
        "n": 198
      },
      {
        "horizon_h": 17,
        "mae": 0.247885864453438,
        "n": 195
      },
      {
        "horizon_h": 18,
        "mae": 0.21948765194605266,
        "n": 126
      },
      {
        "horizon_h": 19,
        "mae": 0.23466936096431712,
        "n": 127
      },
      {
        "horizon_h": 20,
        "mae": 0.2554250949530433,
        "n": 197
      },
      {
        "horizon_h": 21,
        "mae": 0.27249750050191357,
        "n": 197
      },
      {
        "horizon_h": 22,
        "mae": 0.2694024718537624,
        "n": 196
      },
      {
        "horizon_h": 23,
        "mae": 0.273980760327275,
        "n": 193
      },
      {
        "horizon_h": 24,
        "mae": 0.2558472845289443,
        "n": 126
      },
      {
        "horizon_h": 25,
        "mae": 0.26798708307461483,
        "n": 127
      },
      {
        "horizon_h": 26,
        "mae": 0.2847070061430639,
        "n": 196
      },
      {
        "horizon_h": 27,
        "mae": 0.2943013891881826,
        "n": 196
      },
      {
        "horizon_h": 28,
        "mae": 0.29833537175105185,
        "n": 195
      },
      {
        "horizon_h": 29,
        "mae": 0.3047351570327047,
        "n": 193
      },
      {
        "horizon_h": 30,
        "mae": 0.2996360916137696,
        "n": 125
      },
      {
        "horizon_h": 31,
        "mae": 0.3190048929244753,
        "n": 126
      },
      {
        "horizon_h": 32,
        "mae": 0.3117424206855968,
        "n": 195
      },
      {
        "horizon_h": 33,
        "mae": 0.3265609102150829,
        "n": 194
      },
      {
        "horizon_h": 34,
        "mae": 0.3237551413860519,
        "n": 194
      },
      {
        "horizon_h": 35,
        "mae": 0.3309020201365153,
        "n": 192
      },
      {
        "horizon_h": 36,
        "mae": 0.30439034271240245,
        "n": 125
      },
      {
        "horizon_h": 37,
        "mae": 0.31853482836768743,
        "n": 126
      },
      {
        "horizon_h": 38,
        "mae": 0.3240058439205854,
        "n": 195
      },
      {
        "horizon_h": 39,
        "mae": 0.33471826671325056,
        "n": 194
      },
      {
        "horizon_h": 40,
        "mae": 0.3367383927414099,
        "n": 194
      },
      {
        "horizon_h": 41,
        "mae": 0.3434219807386399,
        "n": 192
      },
      {
        "horizon_h": 42,
        "mae": 0.31655712280273446,
        "n": 125
      },
      {
        "horizon_h": 43,
        "mae": 0.32154028907654775,
        "n": 126
      },
      {
        "horizon_h": 44,
        "mae": 0.339358307160053,
        "n": 194
      },
      {
        "horizon_h": 45,
        "mae": 0.3485679241042064,
        "n": 193
      },
      {
        "horizon_h": 46,
        "mae": 0.33826900739126264,
        "n": 193
      },
      {
        "horizon_h": 47,
        "mae": 0.35104201751229647,
        "n": 191
      },
      {
        "horizon_h": 48,
        "mae": 0.32914133225717856,
        "n": 124
      },
      {
        "horizon_h": 49,
        "mae": 0.3337677764892578,
        "n": 125
      },
      {
        "horizon_h": 50,
        "mae": 0.3541513522054246,
        "n": 193
      },
      {
        "horizon_h": 51,
        "mae": 0.3612298925717672,
        "n": 192
      },
      {
        "horizon_h": 52,
        "mae": 0.3598455071449281,
        "n": 192
      },
      {
        "horizon_h": 53,
        "mae": 0.363100865012721,
        "n": 190
      },
      {
        "horizon_h": 54,
        "mae": 0.35642767650325136,
        "n": 123
      },
      {
        "horizon_h": 55,
        "mae": 0.36843173888421826,
        "n": 124
      },
      {
        "horizon_h": 56,
        "mae": 0.3713287005821863,
        "n": 192
      },
      {
        "horizon_h": 57,
        "mae": 0.3789286009304186,
        "n": 191
      },
      {
        "horizon_h": 58,
        "mae": 0.3741595063534084,
        "n": 191
      },
      {
        "horizon_h": 59,
        "mae": 0.37561967133214236,
        "n": 189
      },
      {
        "horizon_h": 60,
        "mae": 0.3627651772847991,
        "n": 123
      },
      {
        "horizon_h": 61,
        "mae": 0.371274911203692,
        "n": 124
      },
      {
        "horizon_h": 62,
        "mae": 0.36958462794621777,
        "n": 192
      },
      {
        "horizon_h": 63,
        "mae": 0.37559239452421983,
        "n": 191
      },
      {
        "horizon_h": 64,
        "mae": 0.3746672854997726,
        "n": 191
      },
      {
        "horizon_h": 65,
        "mae": 0.3763499698941671,
        "n": 189
      },
      {
        "horizon_h": 66,
        "mae": 0.361285912118307,
        "n": 123
      },
      {
        "horizon_h": 67,
        "mae": 0.3676436224291401,
        "n": 124
      },
      {
        "horizon_h": 68,
        "mae": 0.3738190376321682,
        "n": 191
      },
      {
        "horizon_h": 69,
        "mae": 0.37981725793135795,
        "n": 190
      },
      {
        "horizon_h": 70,
        "mae": 0.37073696939568784,
        "n": 190
      },
      {
        "horizon_h": 71,
        "mae": 0.3770651492666691,
        "n": 188
      },
      {
        "horizon_h": 72,
        "mae": 0.3493599672786526,
        "n": 122
      },
      {
        "horizon_h": 73,
        "mae": 0.3579722102095442,
        "n": 123
      },
      {
        "horizon_h": 74,
        "mae": 0.36920208278455224,
        "n": 190
      },
      {
        "horizon_h": 75,
        "mae": 0.37607670233993934,
        "n": 189
      },
      {
        "horizon_h": 76,
        "mae": 0.37023600421885344,
        "n": 189
      },
      {
        "horizon_h": 77,
        "mae": 0.3743249332203585,
        "n": 187
      },
      {
        "horizon_h": 78,
        "mae": 0.3473076717912658,
        "n": 121
      },
      {
        "horizon_h": 79,
        "mae": 0.3551436095941262,
        "n": 122
      },
      {
        "horizon_h": 80,
        "mae": 0.3723770020500061,
        "n": 189
      },
      {
        "horizon_h": 81,
        "mae": 0.37958338209923265,
        "n": 188
      },
      {
        "horizon_h": 82,
        "mae": 0.37571453135064314,
        "n": 188
      },
      {
        "horizon_h": 83,
        "mae": 0.3717371171520603,
        "n": 186
      },
      {
        "horizon_h": 84,
        "mae": 0.35179492698228065,
        "n": 121
      },
      {
        "horizon_h": 85,
        "mae": 0.36309480041754055,
        "n": 122
      },
      {
        "horizon_h": 86,
        "mae": 0.369238464920609,
        "n": 189
      },
      {
        "horizon_h": 87,
        "mae": 0.3757505599488603,
        "n": 188
      },
      {
        "horizon_h": 88,
        "mae": 0.3777339864284435,
        "n": 188
      },
      {
        "horizon_h": 89,
        "mae": 0.37537578254617676,
        "n": 186
      },
      {
        "horizon_h": 90,
        "mae": 0.34712521103788013,
        "n": 121
      },
      {
        "horizon_h": 91,
        "mae": 0.36145746199811096,
        "n": 122
      },
      {
        "horizon_h": 92,
        "mae": 0.3694058205219025,
        "n": 188
      },
      {
        "horizon_h": 93,
        "mae": 0.3748277001202425,
        "n": 187
      },
      {
        "horizon_h": 94,
        "mae": 0.3709101610642704,
        "n": 187
      },
      {
        "horizon_h": 95,
        "mae": 0.36652836773846603,
        "n": 185
      },
      {
        "horizon_h": 96,
        "mae": 0.33346530437469485,
        "n": 120
      },
      {
        "horizon_h": 97,
        "mae": 0.3536980479216773,
        "n": 121
      },
      {
        "horizon_h": 98,
        "mae": 0.3559531828936408,
        "n": 187
      },
      {
        "horizon_h": 99,
        "mae": 0.3646322865639963,
        "n": 186
      },
      {
        "horizon_h": 100,
        "mae": 0.36298594013337165,
        "n": 186
      },
      {
        "horizon_h": 101,
        "mae": 0.36920002647068195,
        "n": 184
      },
      {
        "horizon_h": 102,
        "mae": 0.33266752547576645,
        "n": 119
      },
      {
        "horizon_h": 103,
        "mae": 0.34350203990936273,
        "n": 120
      },
      {
        "horizon_h": 104,
        "mae": 0.35748437963506224,
        "n": 186
      },
      {
        "horizon_h": 105,
        "mae": 0.3598278705493823,
        "n": 185
      },
      {
        "horizon_h": 106,
        "mae": 0.3570717888909417,
        "n": 185
      },
      {
        "horizon_h": 107,
        "mae": 0.3610241405299453,
        "n": 183
      },
      {
        "horizon_h": 108,
        "mae": 0.33783829152083195,
        "n": 119
      },
      {
        "horizon_h": 109,
        "mae": 0.35309402942657475,
        "n": 120
      },
      {
        "horizon_h": 110,
        "mae": 0.3607338587443034,
        "n": 186
      },
      {
        "horizon_h": 111,
        "mae": 0.3658618658942145,
        "n": 185
      },
      {
        "horizon_h": 112,
        "mae": 0.36242376275964683,
        "n": 185
      },
      {
        "horizon_h": 113,
        "mae": 0.3647262823386271,
        "n": 183
      },
      {
        "horizon_h": 114,
        "mae": 0.332049140609613,
        "n": 119
      },
      {
        "horizon_h": 115,
        "mae": 0.3476402997970582,
        "n": 120
      },
      {
        "horizon_h": 116,
        "mae": 0.3574875321259369,
        "n": 185
      },
      {
        "horizon_h": 117,
        "mae": 0.3648360615191252,
        "n": 184
      },
      {
        "horizon_h": 118,
        "mae": 0.36133491681969687,
        "n": 184
      },
      {
        "horizon_h": 119,
        "mae": 0.3659307458898524,
        "n": 182
      },
      {
        "horizon_h": 120,
        "mae": 0.33174673177428166,
        "n": 118
      },
      {
        "horizon_h": 121,
        "mae": 0.3412251544599774,
        "n": 119
      },
      {
        "horizon_h": 122,
        "mae": 0.3481701674668685,
        "n": 184
      },
      {
        "horizon_h": 123,
        "mae": 0.35898532971658337,
        "n": 183
      },
      {
        "horizon_h": 124,
        "mae": 0.356057775737158,
        "n": 183
      },
      {
        "horizon_h": 125,
        "mae": 0.3645688030601207,
        "n": 181
      },
      {
        "horizon_h": 126,
        "mae": 0.32782370575472847,
        "n": 117
      },
      {
        "horizon_h": 127,
        "mae": 0.3377975884130446,
        "n": 118
      },
      {
        "horizon_h": 128,
        "mae": 0.3508972419487251,
        "n": 182
      },
      {
        "horizon_h": 129,
        "mae": 0.3602927560964342,
        "n": 181
      },
      {
        "horizon_h": 130,
        "mae": 0.3576370049576733,
        "n": 181
      },
      {
        "horizon_h": 131,
        "mae": 0.36369359959437203,
        "n": 179
      },
      {
        "horizon_h": 132,
        "mae": 0.3422548244739401,
        "n": 116
      },
      {
        "horizon_h": 133,
        "mae": 0.34950478545620917,
        "n": 117
      },
      {
        "horizon_h": 134,
        "mae": 0.3559255852883692,
        "n": 181
      },
      {
        "horizon_h": 135,
        "mae": 0.3663556257883708,
        "n": 180
      },
      {
        "horizon_h": 136,
        "mae": 0.36257076263427734,
        "n": 181
      },
      {
        "horizon_h": 137,
        "mae": 0.37505529925809894,
        "n": 179
      },
      {
        "horizon_h": 138,
        "mae": 0.3446431931205418,
        "n": 115
      },
      {
        "horizon_h": 139,
        "mae": 0.35459888228054715,
        "n": 116
      },
      {
        "horizon_h": 140,
        "mae": 0.35612903786771116,
        "n": 179
      },
      {
        "horizon_h": 141,
        "mae": 0.37192472822210765,
        "n": 178
      },
      {
        "horizon_h": 142,
        "mae": 0.3678587620484763,
        "n": 179
      },
      {
        "horizon_h": 143,
        "mae": 0.3833919654458257,
        "n": 177
      },
      {
        "horizon_h": 144,
        "mae": 0.3445911909404554,
        "n": 114
      },
      {
        "horizon_h": 145,
        "mae": 0.35304447505785086,
        "n": 115
      },
      {
        "horizon_h": 146,
        "mae": 0.3572859710521912,
        "n": 178
      },
      {
        "horizon_h": 147,
        "mae": 0.3687753052361268,
        "n": 177
      },
      {
        "horizon_h": 148,
        "mae": 0.36121357907070206,
        "n": 178
      },
      {
        "horizon_h": 149,
        "mae": 0.37666818445379086,
        "n": 176
      },
      {
        "horizon_h": 150,
        "mae": 0.34289629100698293,
        "n": 113
      },
      {
        "horizon_h": 151,
        "mae": 0.3534702183907492,
        "n": 114
      },
      {
        "horizon_h": 152,
        "mae": 0.36142247625663454,
        "n": 177
      },
      {
        "horizon_h": 153,
        "mae": 0.37241993058811534,
        "n": 176
      },
      {
        "horizon_h": 154,
        "mae": 0.37096897707147114,
        "n": 177
      },
      {
        "horizon_h": 155,
        "mae": 0.3815142157418388,
        "n": 175
      },
      {
        "horizon_h": 156,
        "mae": 0.35423439836080106,
        "n": 113
      },
      {
        "horizon_h": 157,
        "mae": 0.36753913310536174,
        "n": 114
      },
      {
        "horizon_h": 158,
        "mae": 0.3663983081020204,
        "n": 177
      },
      {
        "horizon_h": 159,
        "mae": 0.3798499952663075,
        "n": 176
      },
      {
        "horizon_h": 160,
        "mae": 0.377996395132636,
        "n": 177
      },
      {
        "horizon_h": 161,
        "mae": 0.38926809692382824,
        "n": 175
      },
      {
        "horizon_h": 162,
        "mae": 0.3583077489802269,
        "n": 113
      },
      {
        "horizon_h": 163,
        "mae": 0.36462545227586185,
        "n": 114
      },
      {
        "horizon_h": 164,
        "mae": 0.3659511631185358,
        "n": 176
      },
      {
        "horizon_h": 165,
        "mae": 0.3771209989275251,
        "n": 175
      },
      {
        "horizon_h": 166,
        "mae": 0.3678061279383574,
        "n": 176
      },
      {
        "horizon_h": 167,
        "mae": 0.38215171879735493,
        "n": 174
      },
      {
        "horizon_h": 168,
        "mae": 0.3468534094946726,
        "n": 112
      }
    ],
    "per_month_test": [
      {
        "month": "2026-03",
        "mae": 0.2725308361139939,
        "n": 6176
      },
      {
        "month": "2026-04",
        "mae": 0.23413510971124493,
        "n": 9683
      },
      {
        "month": "2026-05",
        "mae": 0.4820398551257342,
        "n": 13170
      },
      {
        "month": "2026-06",
        "mae": 0.6744835290411638,
        "n": 1055
      }
    ]
  }
}